Workbook

Sheet TOTAL
A1: LÍNEA BASE DE COSTOS – CUANTIFICACIÓN DE COSTOS TOTALES
A2: PROYECTO: | B2: Vibe Tribe – Aplicación Móvil de Viajes Colaborativos
A3: CÓDIGO: | B3: VBT-2026-01
A4: PERÍODO: | B4: Marzo 2026 – Junio 2026 (16 semanas)
A5: DIRECTORA: | B5: Katlyn Galvis Rodríguez
A6: Tipo de Costo | F6: Monto Total (COP)
A7: COSTO DE OPORTUNIDAD | F7: =Costos_Oportunidad!AA11 -> 10880000
A8: COSTOS HUNDIDOS | F8: =Costos_Hundidos!AA9 -> 2150000
A9: COSTOS VARIABLES | F9: =Costos_Variables!AA14 -> 6550000
A10: COSTOS FIJOS | F10: =Costos_Fijos!AA13 -> 5780000
A11: COSTOS DIRECTOS | F11: =Costos_Directos!AA12 -> 3400000
A12: COSTOS INDIRECTOS | F12: =Costos_Indirectos!AA11 -> 670000
A13: COSTOS CALIDAD | F13: =Costos_Calidad!AA14 -> 10000000
A15: TOTAL COSTOS DE RECURSOS | F15: =SUM(F7:F13) -> 39430000
A16: ★ PRESUPUESTO TOTAL DEL PROYECTO (LÍNEA BASE) | F16: =F15 -> 39430000
A18: NOTAS:
A19: • COSTOS DE OPORTUNIDAD: Valor del tiempo invertido en reuniones y gestión en lugar de desarrollo técnico.
A20: • COSTOS HUNDIDOS: Inversiones iniciales irreversibles en registros de dominio y trabajo técnico descartado.
A21: • COSTOS VARIABLES: Gastos que cambian según el uso de servidores en la nube y consumo de APIs.
A22: • COSTOS FIJOS: Suscripciones recurrentes a herramientas y mantenimiento operativo del entorno de trabajo.
A23: • COSTOS DIRECTOS: Compras únicas de activos digitales, trámites legales de marca y capacitaciones específicas.
A24: • COSTOS INDIRECTOS: Herramientas de apoyo para la gestión de tareas y almacenamiento de código fuente.
A25: • COSTOS DE CALIDAD: Inversión en seguridad, pruebas en dispositivos reales y certificados de protección de datos.

Sheet Costos_Oportunidad
A1: LINEA BASE DE COSTOS – COSTO DE OPORTUNIDAD
A2: PROYECTO: Vibe Tribe – Aplicación Móvil de Viajes Colaborativos
C4: Mes 1 (Mar 2026) | E4: Mes 2 (Abr 2026) | G4: Mes 3 (May 2026) | I4: Mes 4 (Jun 2026) | K4: Mes 5 | M4: Mes 6 | O4: Mes 7 | Q4: Mes 8 | S4: Mes 9 | U4: Mes 10 | W4: Mes 11 | Y4: Mes 12 | AA4: TOTAL
A5: Nombre Recurso / Asignación | B5: Costo Mensual Recurso (COP) | C5: % Asig. | D5: Costo | E5: % Asig. | F5: Costo | G5: % Asig. | H5: Costo | I5: % Asig. | J5: Costo | K5: % Asig. | L5: Costo | M5: % Asig. | N5: Costo | O5: % Asig. | P5: Costo | Q5: % Asig. | R5: Costo | S5: % Asig. | T5: Costo | U5: % Asig. | V5: Costo | W5: % Asig. | X5: Costo | Y5: % Asig. | Z5: Costo | AA5: TOTAL
A6: Oportunidad – Revisión PO (1.1) | B6: 800000 | C6: 100 | D6: =($B6*($C6/100)) -> 800000 | E6: 0 | F6: =($B6*($E6/100)) -> 0 | G6: 0 | H6: =($B6*($G6/100)) -> 0 | I6: 0 | J6: =($B6*($I6/100)) -> 0 | AA6: =D6+F6+H6+J6+L6+N6+P6+R6+T6+V6+X6+Z6 -> 800000
A7: Oportunidad – Retraso Refinamiento (1.3) | B7: 900000 | C7: 100 | D7: =($B7*($C7/100)) -> 900000 | E7: 0 | F7: =($B7*($E7/100)) -> 0 | G7: 0 | H7: =($B7*($G7/100)) -> 0 | I7: 0 | J7: =($B7*($I7/100)) -> 0 | AA7: =D7+F7+H7+J7+L7+N7+P7+R7+T7+V7+X7+Z7 -> 900000
A8: Oportunidad – Cierre vs Expansión (3.5) | B8: 1500000 | C8: 0 | D8: =($B8*($C8/100)) -> 0 | E8: 0 | F8: =($B8*($E8/100)) -> 0 | G8: 0 | H8: =($B8*($G8/100)) -> 0 | I8: 100 | J8: =($B8*($I8/100)) -> 1500000 | AA8: =D8+F8+H8+J8+L8+N8+P8+R8+T8+V8+X8+Z8 -> 1500000
A9: Oportunidad – Ceremonias Scrum (4.2) | B9: 1920000 | C9: 100 | D9: =($B9*($C9/100)) -> 1920000 | E9: 100 | F9: =($B9*($E9/100)) -> 1920000 | G9: 100 | H9: =($B9*($G9/100)) -> 1920000 | I9: 100 | J9: =($B9*($I9/100)) -> 1920000 | AA9: =D9+F9+H9+J9+L9+N9+P9+R9+T9+V9+X9+Z9 -> 7680000
Z11: TOTAL CONSOLIDADO | AA11: =SUM(AA6:AA9) -> 10880000

Sheet Costos_Hundidos
A1: LINEA BASE DE COSTOS – COSTOS HUNDIDOS
A2: PROYECTO: Vibe Tribe – Aplicación Móvil de Viajes Colaborativos
C4: Mes 1 (Mar 2026) | E4: Mes 2 (Abr 2026) | G4: Mes 3 (May 2026) | I4: Mes 4 (Jun 2026) | K4: Mes 5 | M4: Mes 6 | O4: Mes 7 | Q4: Mes 8 | S4: Mes 9 | U4: Mes 10 | W4: Mes 11 | Y4: Mes 12 | AA4: TOTAL
A5: Nombre Recurso / Asignación | B5: Costo Mensual Recurso (COP) | C5: % Asig. | D5: Costo | E5: % Asig. | F5: Costo | G5: % Asig. | H5: Costo | I5: % Asig. | J5: Costo | K5: % Asig. | L5: Costo | M5: % Asig. | N5: Costo | O5: % Asig. | P5: Costo | Q5: % Asig. | R5: Costo | S5: % Asig. | T5: Costo | U5: % Asig. | V5: Costo | W5: % Asig. | X5: Costo | Y5: % Asig. | Z5: Costo | AA5: TOTAL
A6: Registro de Dominio .app / .com (1.2) | B6: 150000 | C6: 100 | D6: =($B6*($C6/100)) -> 150000 | E6: 0 | F6: =($B6*($E6/100)) -> 0 | G6: 0 | H6: =($B6*($G6/100)) -> 0 | I6: 0 | J6: =($B6*($I6/100)) -> 0 | AA6: =D6+F6+H6+J6+L6+N6+P6+R6+T6+V6+X6+Z6 -> 150000
A7: Funcionalidades descartadas/arquitectura (3.2) | B7: 2000000 | C7: 0 | D7: =($B7*($C7/100)) -> 0 | E7: 0 | F7: =($B7*($E7/100)) -> 0 | G7: 0 | H7: =($B7*($G7/100)) -> 0 | I7: 100 | J7: =($B7*($I7/100)) -> 2000000 | AA7: =D7+F7+H7+J7+L7+N7+P7+R7+T7+V7+X7+Z7 -> 2000000
Z9: TOTAL CONSOLIDADO | AA9: =SUM(AA6:AA7) -> 2150000

Sheet Costos_Variables
A1: LINEA BASE DE COSTOS – COSTOS VARIABLES
A2: PROYECTO: Vibe Tribe – Aplicación Móvil de Viajes Colaborativos
C4: Mes 1 (Mar 2026) | E4: Mes 2 (Abr 2026) | G4: Mes 3 (May 2026) | I4: Mes 4 (Jun 2026) | K4: Mes 5 | M4: Mes 6 | O4: Mes 7 | Q4: Mes 8 | S4: Mes 9 | U4: Mes 10 | W4: Mes 11 | Y4: Mes 12 | AA4: TOTAL
A5: Nombre Recurso / Asignación | B5: Costo Mensual Recurso (COP) | C5: % Asig. | D5: Costo | E5: % Asig. | F5: Costo | G5: % Asig. | H5: Costo | I5: % Asig. | J5: Costo | K5: % Asig. | L5: Costo | M5: % Asig. | N5: Costo | O5: % Asig. | P5: Costo | Q5: % Asig. | R5: Costo | S5: % Asig. | T5: Costo | U5: % Asig. | V5: Costo | W5: % Asig. | X5: Costo | Y5: % Asig. | Z5: Costo | AA5: TOTAL
A6: Runners GitHub Actions (1.4) | B6: 37500 | C6: 100 | D6: =($B6*($C6/100)) -> 37500 | E6: 100 | F6: =($B6*($E6/100)) -> 37500 | G6: 100 | H6: =($B6*($G6/100)) -> 37500 | I6: 100 | J6: =($B6*($I6/100)) -> 37500 | AA6: =D6+F6+H6+J6+L6+N6+P6+R6+T6+V6+X6+Z6 -> 150000
A7: Verificación SMS/OTP (2.1) | B7: 125000 | C7: 0 | D7: =($B7*($C7/100)) -> 0 | E7: 100 | F7: =($B7*($E7/100)) -> 125000 | G7: 100 | H7: =($B7*($G7/100)) -> 125000 | I7: 200 | J7: =($B7*($I7/100)) -> 250000 | AA7: =D7+F7+H7+J7+L7+N7+P7+R7+T7+V7+X7+Z7 -> 500000
A8: Google Maps API - Routes (2.2) | B8: 500000 | C8: 0 | D8: =($B8*($C8/100)) -> 0 | E8: 100 | F8: =($B8*($E8/100)) -> 500000 | G8: 100 | H8: =($B8*($G8/100)) -> 500000 | I8: 200 | J8: =($B8*($I8/100)) -> 1000000 | AA8: =D8+F8+H8+J8+L8+N8+P8+R8+T8+V8+X8+Z8 -> 2000000
A9: Tráfico de Datos Real-time (2.3) | B9: 100000 | C9: 0 | D9: =($B9*($C9/100)) -> 0 | E9: 100 | F9: =($B9*($E9/100)) -> 100000 | G9: 100 | H9: =($B9*($G9/100)) -> 100000 | I9: 200 | J9: =($B9*($I9/100)) -> 200000 | AA9: =D9+F9+H9+J9+L9+N9+P9+R9+T9+V9+X9+Z9 -> 400000
A10: AWS Rekognition (Moderación IA) (2.4) | B10: 625000 | C10: 0 | D10: =($B10*($C10/100)) -> 0 | E10: 100 | F10: =($B10*($E10/100)) -> 625000 | G10: 100 | H10: =($B10*($G10/100)) -> 625000 | I10: 200 | J10: =($B10*($I10/100)) -> 1250000 | AA10: =D10+F10+H10+J10+L10+N10+P10+R10+T10+V10+X10+Z10 -> 2500000
A11: AWS Device Farm - Testing (3.1) | B11: 600000 | C11: 0 | D11: =($B11*($C11/100)) -> 0 | E11: 0 | F11: =($B11*($E11/100)) -> 0 | G11: 0 | H11: =($B11*($G11/100)) -> 0 | I11: 100 | J11: =($B11*($I11/100)) -> 600000 | AA11: =D11+F11+H11+J11+L11+N11+P11+R11+T11+V11+X11+Z11 -> 600000
A12: Data Transfer Out - AWS (3.3) | B12: 400000 | C12: 0 | D12: =($B12*($C12/100)) -> 0 | E12: 0 | F12: =($B12*($E12/100)) -> 0 | G12: 0 | H12: =($B12*($G12/100)) -> 0 | I12: 100 | J12: =($B12*($I12/100)) -> 400000 | AA12: =D12+F12+H12+J12+L12+N12+P12+R12+T12+V12+X12+Z12 -> 400000
Z14: TOTAL CONSOLIDADO | AA14: =SUM(AA6:AA12) -> 6550000

Sheet Costos_Fijos
A1: LINEA BASE DE COSTOS – COSTOS FIJOS
A2: PROYECTO: Vibe Tribe – Aplicación Móvil de Viajes Colaborativos
C4: Mes 1 (Mar 2026) | E4: Mes 2 (Abr 2026) | G4: Mes 3 (May 2026) | I4: Mes 4 (Jun 2026) | K4: Mes 5 | M4: Mes 6 | O4: Mes 7 | Q4: Mes 8 | S4: Mes 9 | U4: Mes 10 | W4: Mes 11 | Y4: Mes 12 | AA4: TOTAL
A5: Nombre Recurso / Asignación | B5: Costo Mensual Recurso (COP) | C5: % Asig. | D5: Costo | E5: % Asig. | F5: Costo | G5: % Asig. | H5: Costo | I5: % Asig. | J5: Costo | K5: % Asig. | L5: Costo | M5: % Asig. | N5: Costo | O5: % Asig. | P5: Costo | Q5: % Asig. | R5: Costo | S5: % Asig. | T5: Costo | U5: % Asig. | V5: Costo | W5: % Asig. | X5: Costo | Y5: % Asig. | Z5: Costo | AA5: TOTAL
A6: Licencia Figma Professional (1.1) | B6: 150000 | C6: 100 | D6: =($B6*($C6/100)) -> 150000 | E6: 100 | F6: =($B6*($E6/100)) -> 150000 | G6: 100 | H6: =($B6*($G6/100)) -> 150000 | I6: 100 | J6: =($B6*($I6/100)) -> 150000 | AA6: =D6+F6+H6+J6+L6+N6+P6+R6+T6+V6+X6+Z6 -> 600000
A7: AWS Support Plan Business (1.2) | B7: 100000 | C7: 100 | D7: =($B7*($C7/100)) -> 100000 | E7: 100 | F7: =($B7*($E7/100)) -> 100000 | G7: 100 | H7: =($B7*($G7/100)) -> 100000 | I7: 100 | J7: =($B7*($I7/100)) -> 100000 | AA7: =D7+F7+H7+J7+L7+N7+P7+R7+T7+V7+X7+Z7 -> 400000
A8: Backups DB y Retención (2.3) | B8: 100000 | C8: 0 | D8: =($B8*($C8/100)) -> 0 | E8: 100 | F8: =($B8*($E8/100)) -> 100000 | G8: 100 | H8: =($B8*($G8/100)) -> 100000 | I8: 100 | J8: =($B8*($I8/100)) -> 100000 | AA8: =D8+F8+H8+J8+L8+N8+P8+R8+T8+V8+X8+Z8 -> 300000
A9: AWS Reserved Instances - Prepago (3.3) | B9: 3800000 | C9: 0 | D9: =($B9*($C9/100)) -> 0 | E9: 0 | F9: =($B9*($E9/100)) -> 0 | G9: 0 | H9: =($B9*($G9/100)) -> 0 | I9: 100 | J9: =($B9*($I9/100)) -> 3800000 | AA9: =D9+F9+H9+J9+L9+N9+P9+R9+T9+V9+X9+Z9 -> 3800000
A10: Amortización Laptops Equipo (4.1) | B10: 120000 | C10: 100 | D10: =($B10*($C10/100)) -> 120000 | E10: 100 | F10: =($B10*($E10/100)) -> 120000 | G10: 100 | H10: =($B10*($G10/100)) -> 120000 | I10: 100 | J10: =($B10*($I10/100)) -> 120000 | AA10: =D10+F10+H10+J10+L10+N10+P10+R10+T10+V10+X10+Z10 -> 480000
A11: Licencia Notion/Knowledge Base (4.3) | B11: 50000 | C11: 100 | D11: =($B11*($C11/100)) -> 50000 | E11: 100 | F11: =($B11*($E11/100)) -> 50000 | G11: 100 | H11: =($B11*($G11/100)) -> 50000 | I11: 100 | J11: =($B11*($I11/100)) -> 50000 | AA11: =D11+F11+H11+J11+L11+N11+P11+R11+T11+V11+X11+Z11 -> 200000
Z13: TOTAL CONSOLIDADO | AA13: =SUM(AA6:AA11) -> 5780000

Sheet Costos_Directos
A1: LINEA BASE DE COSTOS – COSTOS DIRECTOS
A2: PROYECTO: Vibe Tribe – Aplicación Móvil de Viajes Colaborativos
C4: Mes 1 (Mar 2026) | E4: Mes 2 (Abr 2026) | G4: Mes 3 (May 2026) | I4: Mes 4 (Jun 2026) | K4: Mes 5 | M4: Mes 6 | O4: Mes 7 | Q4: Mes 8 | S4: Mes 9 | U4: Mes 10 | W4: Mes 11 | Y4: Mes 12 | AA4: TOTAL
A5: Nombre Recurso / Asignación | B5: Costo Mensual Recurso (COP) | C5: % Asig. | D5: Costo | E5: % Asig. | F5: Costo | G5: % Asig. | H5: Costo | I5: % Asig. | J5: Costo | K5: % Asig. | L5: Costo | M5: % Asig. | N5: Costo | O5: % Asig. | P5: Costo | Q5: % Asig. | R5: Costo | S5: % Asig. | T5: Costo | U5: % Asig. | V5: Costo | W5: % Asig. | X5: Costo | Y5: % Asig. | Z5: Costo | AA5: TOTAL
A6: UI Kit Viajes (Assets Gráficos) (1.1) | B6: 350000 | C6: 100 | D6: =($B6*($C6/100)) -> 350000 | E6: 0 | F6: =($B6*($E6/100)) -> 0 | G6: 0 | H6: =($B6*($G6/100)) -> 0 | I6: 0 | J6: =($B6*($I6/100)) -> 0 | AA6: =D6+F6+H6+J6+L6+N6+P6+R6+T6+V6+X6+Z6 -> 350000
A7: Capacitación Seguridad OAuth2 (2.1) | B7: 1000000 | C7: 0 | D7: =($B7*($C7/100)) -> 0 | E7: 100 | F7: =($B7*($E7/100)) -> 1000000 | G7: 0 | H7: =($B7*($G7/100)) -> 0 | I7: 0 | J7: =($B7*($I7/100)) -> 0 | AA7: =D7+F7+H7+J7+L7+N7+P7+R7+T7+V7+X7+Z7 -> 1000000
A8: Registro Marca Vibe Tribe - SIC (3.3) | B8: 1500000 | C8: 0 | D8: =($B8*($C8/100)) -> 0 | E8: 0 | F8: =($B8*($E8/100)) -> 0 | G8: 0 | H8: =($B8*($G8/100)) -> 0 | I8: 100 | J8: =($B8*($I8/100)) -> 1500000 | AA8: =D8+F8+H8+J8+L8+N8+P8+R8+T8+V8+X8+Z8 -> 1500000
A9: Alquiler Plataforma Webinar (3.4) | B9: 300000 | C9: 0 | D9: =($B9*($C9/100)) -> 0 | E9: 0 | F9: =($B9*($E9/100)) -> 0 | G9: 0 | H9: =($B9*($G9/100)) -> 0 | I9: 100 | J9: =($B9*($I9/100)) -> 300000 | AA9: =D9+F9+H9+J9+L9+N9+P9+R9+T9+V9+X9+Z9 -> 300000
A10: Gastos Notariales Liquidación (3.5) | B10: 250000 | C10: 0 | D10: =($B10*($C10/100)) -> 0 | E10: 0 | F10: =($B10*($E10/100)) -> 0 | G10: 0 | H10: =($B10*($G10/100)) -> 0 | I10: 100 | J10: =($B10*($I10/100)) -> 250000 | AA10: =D10+F10+H10+J10+L10+N10+P10+R10+T10+V10+X10+Z10 -> 250000
Z12: TOTAL CONSOLIDADO | AA12: =SUM(AA6:AA10) -> 3400000

Sheet Costos_Indirectos
A1: LINEA BASE DE COSTOS – COSTOS INDIRECTOS
A2: PROYECTO: Vibe Tribe – Aplicación Móvil de Viajes Colaborativos
C4: Mes 1 (Mar 2026) | E4: Mes 2 (Abr 2026) | G4: Mes 3 (May 2026) | I4: Mes 4 (Jun 2026) | K4: Mes 5 | M4: Mes 6 | O4: Mes 7 | Q4: Mes 8 | S4: Mes 9 | U4: Mes 10 | W4: Mes 11 | Y4: Mes 12 | AA4: TOTAL
A5: Nombre Recurso / Asignación | B5: Costo Mensual Recurso (COP) | C5: % Asig. | D5: Costo | E5: % Asig. | F5: Costo | G5: % Asig. | H5: Costo | I5: % Asig. | J5: Costo | K5: % Asig. | L5: Costo | M5: % Asig. | N5: Costo | O5: % Asig. | P5: Costo | Q5: % Asig. | R5: Costo | S5: % Asig. | T5: Costo | U5: % Asig. | V5: Costo | W5: % Asig. | X5: Costo | Y5: % Asig. | Z5: Costo | AA5: TOTAL
A6: GitHub Team (Repositorio) (1.2) | B6: 30000 | C6: 100 | D6: =($B6*($C6/100)) -> 30000 | E6: 100 | F6: =($B6*($E6/100)) -> 30000 | G6: 100 | H6: =($B6*($G6/100)) -> 30000 | I6: 100 | J6: =($B6*($I6/100)) -> 30000 | AA6: =D6+F6+H6+J6+L6+N6+P6+R6+T6+V6+X6+Z6 -> 120000
A7: Almacenamiento S3 Base (2.2) | B7: 100000 | C7: 0 | D7: =($B7*($C7/100)) -> 0 | E7: 0 | F7: =($B7*($E7/100)) -> 0 | G7: 0 | H7: =($B7*($G7/100)) -> 0 | I7: 100 | J7: =($B7*($I7/100)) -> 100000 | AA7: =D7+F7+H7+J7+L7+N7+P7+R7+T7+V7+X7+Z7 -> 100000
A8: Licencia Adobe CC (Manuales) (3.4) | B8: 50000 | C8: 0 | D8: =($B8*($C8/100)) -> 0 | E8: 100 | F8: =($B8*($E8/100)) -> 50000 | G8: 100 | H8: =($B8*($G8/100)) -> 50000 | I8: 100 | J8: =($B8*($I8/100)) -> 50000 | AA8: =D8+F8+H8+J8+L8+N8+P8+R8+T8+V8+X8+Z8 -> 150000
A9: Jira / Asana Premium (4.1) | B9: 75000 | C9: 100 | D9: =($B9*($C9/100)) -> 75000 | E9: 100 | F9: =($B9*($E9/100)) -> 75000 | G9: 100 | H9: =($B9*($G9/100)) -> 75000 | I9: 100 | J9: =($B9*($I9/100)) -> 75000 | AA9: =D9+F9+H9+J9+L9+N9+P9+R9+T9+V9+X9+Z9 -> 300000
Z11: TOTAL CONSOLIDADO | AA11: =SUM(AA6:AA9) -> 670000
U24: }

Sheet Costos_Calidad
A1: LINEA BASE DE COSTOS – COSTOS CALIDAD
A2: PROYECTO: Vibe Tribe – Aplicación Móvil de Viajes Colaborativos
C4: Mes 1 (Mar 2026) | E4: Mes 2 (Abr 2026) | G4: Mes 3 (May 2026) | I4: Mes 4 (Jun 2026) | K4: Mes 5 | M4: Mes 6 | O4: Mes 7 | Q4: Mes 8 | S4: Mes 9 | U4: Mes 10 | W4: Mes 11 | Y4: Mes 12 | AA4: TOTAL
A5: Nombre Recurso / Asignación | B5: Costo Mensual Recurso (COP) | C5: % Asig. | D5: Costo | E5: % Asig. | F5: Costo | G5: % Asig. | H5: Costo | I5: % Asig. | J5: Costo | K5: % Asig. | L5: Costo | M5: % Asig. | N5: Costo | O5: % Asig. | P5: Costo | Q5: % Asig. | R5: Costo | S5: % Asig. | T5: Costo | U5: % Asig. | V5: Costo | W5: % Asig. | X5: Costo | Y5: % Asig. | Z5: Costo | AA5: TOTAL
A6: Refinamiento Técnico Preventivo (1.3) | B6: 1200000 | C6: 100 | D6: =($B6*($C6/100)) -> 1200000 | E6: 0 | F6: =($B6*($E6/100)) -> 0 | G6: 0 | H6: =($B6*($G6/100)) -> 0 | I6: 0 | J6: =($B6*($I6/100)) -> 0 | AA6: =D6+F6+H6+J6+L6+N6+P6+R6+T6+V6+X6+Z6 -> 1200000
A7: SonarQube Cloud - Vulnerabilidades (1.4) | B7: 87500 | C7: 100 | D7: =($B7*($C7/100)) -> 87500 | E7: 100 | F7: =($B7*($E7/100)) -> 87500 | G7: 100 | H7: =($B7*($G7/100)) -> 87500 | I7: 100 | J7: =($B7*($I7/100)) -> 87500 | AA7: =D7+F7+H7+J7+L7+N7+P7+R7+T7+V7+X7+Z7 -> 350000
A8: Certificado SSL EV (2.1) | B8: 450000 | C8: 100 | D8: =($B8*($C8/100)) -> 450000 | E8: 0 | F8: =($B8*($E8/100)) -> 0 | G8: 0 | H8: =($B8*($G8/100)) -> 0 | I8: 0 | J8: =($B8*($I8/100)) -> 0 | AA8: =D8+F8+H8+J8+L8+N8+P8+R8+T8+V8+X8+Z8 -> 450000
A9: User Testing Externo (2.4) | B9: 1200000 | C9: 0 | D9: =($B9*($C9/100)) -> 0 | E9: 0 | F9: =($B9*($E9/100)) -> 0 | G9: 100 | H9: =($B9*($G9/100)) -> 1200000 | I9: 0 | J9: =($B9*($I9/100)) -> 0 | AA9: =D9+F9+H9+J9+L9+N9+P9+R9+T9+V9+X9+Z9 -> 1200000
A10: Pentesting Externo (3.1) | B10: 4500000 | C10: 0 | D10: =($B10*($C10/100)) -> 0 | E10: 0 | F10: =($B10*($E10/100)) -> 0 | G10: 0 | H10: =($B10*($G10/100)) -> 0 | I10: 100 | J10: =($B10*($I10/100)) -> 4500000 | AA10: =D10+F10+H10+J10+L10+N10+P10+R10+T10+V10+X10+Z10 -> 4500000
A11: Re-testeo de Falla Interna (3.2) | B11: 800000 | C11: 0 | D11: =($B11*($C11/100)) -> 0 | E11: 0 | F11: =($B11*($E11/100)) -> 0 | G11: 0 | H11: =($B11*($G11/100)) -> 0 | I11: 100 | J11: =($B11*($I11/100)) -> 800000 | AA11: =D11+F11+H11+J11+L11+N11+P11+R11+T11+V11+X11+Z11 -> 800000
A12: Revisión Arquitectura Experta (4.3) | B12: 1500000 | C12: 0 | D12: =($B12*($C12/100)) -> 0 | E12: 0 | F12: =($B12*($E12/100)) -> 0 | G12: 0 | H12: =($B12*($G12/100)) -> 0 | I12: 100 | J12: =($B12*($I12/100)) -> 1500000 | AA12: =D12+F12+H12+J12+L12+N12+P12+R12+T12+V12+X12+Z12 -> 1500000
Z14: TOTAL CONSOLIDADO | AA14: =SUM(AA6:AA12) -> 10000000
